openrelik_common/__init__.py
openrelik_common/logging.py
openrelik_common/telemetry.py
openrelik_common-0.7.6.dist-info/METADATA
openrelik_common-0.7.6.dist-info/WHEEL
openrelik_common-0.7.6.dist-info/licenses/LICENSE
openrelik_common-0.7.6.dist-info/RECORD
